{
  "__type__": "cc.SpriteFrame",
  "content": {
    "name": "enemy5-sheet0",
    "atlas": "",
    "rect": {
      "x": 0,
      "y": 0,
      "width": 86,
      "height": 7
    },
    "offset": {
      "x": 0,
      "y": 0
    },
    "originalSize": {
      "width": 86,
      "height": 7
    },
    "rotated": false,
    "capInsets": [
      0,
      0,
      0,
      0
    ],
    "vertices": {
      "rawPosition": [
        -43,
        -3.5,
        0,
        43,
        -3.5,
        0,
        -43,
        3.5,
        0,
        43,
        3.5,
        0
      ],
      "indexes": [
        0,
        1,
        2,
        2,
        1,
        3
      ],
      "uv": [
        0,
        7,
        86,
        7,
        0,
        0,
        86,
        0
      ],
      "nuv": [
        0,
        0,
        1,
        0,
        0,
        1,
        1,
        1
      ],
      "minPos": {
        "x": -43,
        "y": -3.5,
        "z": 0
      },
      "maxPos": {
        "x": 43,
        "y": 3.5,
        "z": 0
      }
    },
    "texture": "8bdec78e-8699-4d5e-892c-987d029e0d14@6c48a",
    "packable": true,
    "pixelsToUnit": 100,
    "pivot": {
      "x": 0.5,
      "y": 0.5
    },
    "meshType": 0
  }
}